dictionary/__init__.py
dictionary/dictionary.py
Dictionary_CI-2.0.0.dist-info/METADATA
Dictionary_CI-2.0.0.dist-info/WHEEL
Dictionary_CI-2.0.0.dist-info/top_level.txt
Dictionary_CI-2.0.0.dist-info/RECORD
